__init__.py
sample/sample.py
sampleproject_pub-0.0.4.dist-info/METADATA
sampleproject_pub-0.0.4.dist-info/WHEEL
sampleproject_pub-0.0.4.dist-info/entry_points.txt
sampleproject_pub-0.0.4.dist-info/top_level.txt
sampleproject_pub-0.0.4.dist-info/RECORD
